aiyc1v1/__init__.py
aiyc1v1/__version__.py
aiyc1v1/aiycwordcloud.py
aiyc1v1/simplenlp.py
aiyc1v1/DelayWait/DelayWait.py
aiyc1v1/DelayWait/__init__.py
aiyc1v1/DelayWait/__version__.py
aiyc1v1/GameFunction/GameFunction.py
aiyc1v1/GameFunction/__init__.py
aiyc1v1/NoteSearch/DataManager.py
aiyc1v1/NoteSearch/DataRead.py
aiyc1v1/NoteSearch/NoteSearch.py
aiyc1v1/NoteSearch/SEARCH_ENGINE.py
aiyc1v1/NoteSearch/__init__.py
aiyc1v1/NoteSearch/__version__.py
aiyc1v1/class_coder/GameBase.py
aiyc1v1/class_coder/Q1.py
aiyc1v1/class_coder/__init__.py
aiyc1v1/class_coder/__version__.py
aiyc1v1/class_coder/simplenlp.py
aiyc1v1/class_coder/wordcloud.py
aiyc1v1/simplesearch/DataManager.py
aiyc1v1/simplesearch/DataManager_old.py
aiyc1v1/simplesearch/SimpleSearch.py
aiyc1v1/simplesearch/__init__.py
aiycsnlp/__init__.py
aiycsnlp/__version__.py
aiycsnlp/aiycsnlp.py
aiycsnlp/aiycwordcloud.py
aiycsnlp/wordcloud.py
tests/__init__.py
tests/aiycsnlp-Tester.py
aiyc1v1-0.0.45.dist-info/LICENSE
aiyc1v1-0.0.45.dist-info/METADATA
aiyc1v1-0.0.45.dist-info/WHEEL
aiyc1v1-0.0.45.dist-info/top_level.txt
aiyc1v1-0.0.45.dist-info/RECORD
