Metadata-Version: 2.1
Name: aiyc1v1
Version: 0.0.45
Summary: AI悦创·编程一对一教学代码库,长期招收编程一对一学员,微信:Jiabcdefh
Home-page: https://github.com/AndersonHJB/aiyc1v1
Author: Bornforthis
Author-email: bornforthis@bornforthis.com
License: MIT
Classifier: License :: OSI Approved :: MIT License
Classifier: Programming Language :: Python
Classifier: Programming Language :: Python :: 3
Classifier: Programming Language :: Python :: 3.6
Classifier: Programming Language :: Python :: Implementation :: CPython
Classifier: Programming Language :: Python :: Implementation :: PyPy
Requires-Python: >=3.6.0
License-File: LICENSE
Requires-Dist: pyecharts
Requires-Dist: faker
Requires-Dist: pandas
Requires-Dist: openpyxl
Requires-Dist: xlrd
Requires-Dist: requests
